[{"model": "posts.category", "pk": 1, "fields": {"name": "Tasty Bites", "description": "Crave-worthy culinary creations", "image": "", "slug": "tasty-bites", "date_modified": "2016-03-08T23:14:42.708Z", "date_added": "2016-03-08T23:14:42.708Z"}}, {"model": "posts.category", "pk": 2, "fields": {"name": "Adventures", "description": "Any and all adventures", "image": "", "slug": "adventures", "date_modified": "2016-03-08T23:15:43.283Z", "date_added": "2016-03-08T23:15:43.284Z"}}, {"model": "posts.category", "pk": 3, "fields": {"name": "Graphics", "description": "Gratifying graphics", "image": "", "slug": "graphics", "date_modified": "2016-03-08T23:16:40.294Z", "date_added": "2016-03-08T23:16:40.294Z"}}]